litecoinpy/__init__.py
litecoinpy/exceptions.py
litecoinpy/litecoinpy.py
litecoinpy/main.py
litecoinpy/utils.py
tests/__init__.py
tests/test.py
litecoinpy-0.1.0.dist-info/METADATA
litecoinpy-0.1.0.dist-info/WHEEL
litecoinpy-0.1.0.dist-info/RECORD
